Metadata-Version: 2.4
Name: bioflow-insight
Version: 2.0.11
Summary: A software to extract and analyze the structure and associated metadata from a Nextflow workflow.
Author: George Marchment
Project-URL: Homepage, https://gitlab.liris.cnrs.fr/sharefair/bioflow-insight
Project-URL: Issues, https://gitlab.liris.cnrs.fr/sharefair/bioflow-insight/-/issues
Classifier: Programming Language :: Python :: 3
Classifier: Operating System :: OS Independent
Requires-Python: >=3.8
License-File: LICENSE
Requires-Dist: graphviz==0.20.1
Requires-Dist: networkx~=3.2.1; python_version >= "3.9"
Requires-Dist: networkx~=3.1; python_version == "3.8"
Requires-Dist: numpy~=1.26.1; python_version >= "3.9"
Requires-Dist: numpy~=1.24.4; python_version == "3.8"
Requires-Dist: sympy==1.9
Requires-Dist: parsimonious==0.10.0
Requires-Dist: click
Requires-Dist: jpype1==1.6.0
Provides-Extra: dev
Requires-Dist: build; extra == "dev"
Requires-Dist: twine; extra == "dev"
Requires-Dist: coverage; extra == "dev"
Requires-Dist: black~=23.12.0; extra == "dev"
Dynamic: license-file
